[
  {
    "iconUri": "https://media.licdn.com/dms/image/v2/C510BAQEj90PdyVekDw/company-logo_100_100/company-logo_100_100/0/1631333533529?e=1757548800&v=beta&t=jpElkkDR8mq-qjs2obhpOyEZV2BBuPnc0g1HY7lZ2NE",
    "school": "Hong Kong Design Institute (HKDI)",
    "degree": "Higher Diploma in Software Engineering",
    "fieldOfStudy": "Computer Software Engineering",
    "grade": "pass",
    "startDate": "2022-09-01T00:00:00.000Z",
    "endDate": "2024-07-01T00:00:00.000Z"
  },
  {
    "iconUri": "https://media.licdn.com/dms/image/v2/C4E0BAQENyV1X2qPs_w/company-logo_100_100/company-logo_100_100/0/1631307848688?e=1757548800&v=beta&t=gWHo4gbmLN2nCxVBoPFShvgOgYz9bgSYTsDxU65v8vo",
    "school": "University of the West of England",
    "degree": "Bachelor of Technology - BTech",
    "fieldOfStudy": "BSC (HONS) Information Technology",
    "grade": "Second Class (Upper Division)",
    "startDate": "2024-09-01T00:00:00.000Z",
    "endDate": "2025-07-01T00:00:00.000Z",
    "certUri": "Chan Ho Lam - Chan Ho Lam  - INFORMATION TECHNOLOGY - Certificate - 24065706.pdf"
  }
]
